fyle_accounting_library/__init__.py
fyle_accounting_library/common_resources/__init__.py
fyle_accounting_library/common_resources/apps.py
fyle_accounting_library/common_resources/enums.py
fyle_accounting_library/common_resources/helpers.py
fyle_accounting_library/common_resources/logging_middleware.py
fyle_accounting_library/common_resources/model_fields.py
fyle_accounting_library/common_resources/models.py
fyle_accounting_library/common_resources/serializers.py
fyle_accounting_library/common_resources/urls.py
fyle_accounting_library/common_resources/views.py
fyle_accounting_library/common_resources/migrations/0001_initial.py
fyle_accounting_library/common_resources/migrations/__init__.py
fyle_accounting_library/fyle_platform/__init__.py
fyle_accounting_library/fyle_platform/actions.py
fyle_accounting_library/fyle_platform/apps.py
fyle_accounting_library/fyle_platform/branding.py
fyle_accounting_library/fyle_platform/constants.py
fyle_accounting_library/fyle_platform/enums.py
fyle_accounting_library/fyle_platform/exceptions.py
fyle_accounting_library/fyle_platform/helpers.py
fyle_accounting_library/fyle_platform/models.py
fyle_accounting_library/rabbitmq/__init__.py
fyle_accounting_library/rabbitmq/apps.py
fyle_accounting_library/rabbitmq/connector.py
fyle_accounting_library/rabbitmq/data_class.py
fyle_accounting_library/rabbitmq/enums.py
fyle_accounting_library/rabbitmq/helpers.py
fyle_accounting_library/rabbitmq/models.py
fyle_accounting_library/rabbitmq/migrations/0001_initial.py
fyle_accounting_library/rabbitmq/migrations/0002_alter_failedevent_error_traceback.py
fyle_accounting_library/rabbitmq/migrations/0003_alter_failedevent_created_at_and_more.py
fyle_accounting_library/rabbitmq/migrations/0004_failedevent_is_resolved.py
fyle_accounting_library/rabbitmq/migrations/__init__.py
fyle_accounting_library/system_comments/__init__.py
fyle_accounting_library/system_comments/apps.py
fyle_accounting_library/system_comments/models.py
fyle_accounting_mappings-3.0.0.dist-info/licenses/LICENSE
fyle_accounting_mappings-3.0.0.dist-info/METADATA
fyle_accounting_mappings-3.0.0.dist-info/WHEEL
fyle_accounting_mappings-3.0.0.dist-info/top_level.txt
fyle_accounting_mappings-3.0.0.dist-info/RECORD
