Metadata-Version: 2.4
Name: fyle-accounting-mappings
Version: 3.0.0
Summary: Django application to store the fyle accounting mappings in a generic manner
Home-page: https://github.com/fylein/fyle-accounting-mappings
Author: Shwetabh Kumar
Author-email: shwetabh.kumar@fyle.in
License: MIT
Keywords: fyle,rest,django-rest-framework,api,python,accounting
Classifier: Framework :: Django
Classifier: Intended Audience :: Developers
Classifier: Intended Audience :: System Administrators
Classifier: Operating System :: OS Independent
Classifier: Topic :: Software Development
License-File: LICENSE
Requires-Dist: django>=3.0.2
Requires-Dist: django-rest-framework>=0.1.0
Dynamic: author
Dynamic: author-email
Dynamic: classifier
Dynamic: description
Dynamic: description-content-type
Dynamic: home-page
Dynamic: keywords
Dynamic: license
Dynamic: license-file
Dynamic: requires-dist
Dynamic: summary
